konsepy/__init__.py
konsepy/bio_tag.py
konsepy/bio_tag_corpus.py
konsepy/bio_tag_sentence.py
konsepy/cli.py
konsepy/constants.py
konsepy/corpus2jsonl.py
konsepy/create_bio_dataset.py
konsepy/engine.py
konsepy/get_text_snippets.py
konsepy/importer.py
konsepy/main.py
konsepy/regex.py
konsepy/run4snippets.py
konsepy/run_all.py
konsepy/rxsearch.py
konsepy/rxutils.py
konsepy/textio.py
konsepy/train_on_bio_dataset.py
konsepy/types.py
konsepy/context/__init__.py
konsepy/context/contexts.py
konsepy/context/negation.py
konsepy/context/other_subject.py
konsepy-0.3.2.dist-info/METADATA
konsepy-0.3.2.dist-info/WHEEL
konsepy-0.3.2.dist-info/entry_points.txt
konsepy-0.3.2.dist-info/top_level.txt
konsepy-0.3.2.dist-info/RECORD
