Metadata-Version: 2.4
Name: konsepy
Version: 0.3.2
Summary: Framework for build NLP information extraction systems using regular expressions.
Author-email: dcronkite <dcronkite+pypi@gmail.com>
Project-URL: Home, https://github.com/kpwhri/konsepy
Keywords: nlp
Classifier: Development Status :: 5 - Production/Stable
Classifier: Intended Audience :: Science/Research
Classifier: Programming Language :: Python :: 3 :: Only
Classifier: Programming Language :: Python :: 3.10
Classifier: Programming Language :: Python :: 3.11
Classifier: Programming Language :: Python :: 3.12
Classifier: Programming Language :: Python :: 3.13
Classifier: Topic :: Text Processing :: Linguistic
Classifier: License :: OSI Approved :: MIT License
Classifier: Intended Audience :: Healthcare Industry
Requires-Python: >=3.10
Requires-Dist: loguru>=0.7.0
Provides-Extra: dev
Requires-Dist: pytest>=9.0.0; extra == "dev"
Provides-Extra: ssplit
Requires-Dist: spacy; extra == "ssplit"
Provides-Extra: sas
Requires-Dist: sas7bdat; extra == "sas"
Provides-Extra: model
Requires-Dist: datasets; extra == "model"
Requires-Dist: transformers; extra == "model"
Provides-Extra: all
Requires-Dist: sas; extra == "all"
Requires-Dist: model; extra == "all"
